README.md
setup.cfg
setup.py
hiker/__init__.py
hiker/hiker.py
hiker.egg-info/PKG-INFO
hiker.egg-info/SOURCES.txt
hiker.egg-info/dependency_links.txt
hiker.egg-info/requires.txt
hiker.egg-info/top_level.txt