Metadata-Version: 2.1
Name: hiker
Version: 0.1.2
Summary: UNKNOWN
Home-page: UNKNOWN
Author: Mimo Tilbich
License: MIT
Platform: UNKNOWN
Requires-Python: >=3.7
Provides-Extra: dev
